dart_ops_engine/__init__.py
dart_ops_engine/action_command.py
dart_ops_engine/action_run.py
dart_ops_engine/cache_manager.py
dart_ops_engine/dart_ops_engine.py
dart_ops_engine/define.py
dart_ops_engine/env.py
dart_ops_engine/execute.py
dart_ops_engine-0.2.0.dist-info/METADATA
dart_ops_engine-0.2.0.dist-info/WHEEL
dart_ops_engine-0.2.0.dist-info/top_level.txt
dart_ops_engine-0.2.0.dist-info/RECORD
