Metadata-Version: 2.1
Name: dart_ops_engine
Version: 0.2.0
Summary: 一个可以被Dart dart_ops_engine执行的Python脚本引擎
Home-page: https://github.com/DartOpsHub/dart_ops_engine_python
Author: 君赏
Author-email: josercc@163.com
